pyxela/__init__.py
pyxela/constants.py
pyxela/graph.py
pyxela/handler.py
pyxela/instant_recording.py
pyxela/pixel.py
pyxela/playground.py
pyxela/profile.py
pyxela/retina.py
pyxela/tokenizer.py
pyxela/user.py
pyxela/webhoock.py
pyxela/model/__init__.py
pyxela/model/colors.py
pyxela/model/graph_config.py
pyxela/model/user_config.py
pyxela-0.0.0.dist-info/METADATA
pyxela-0.0.0.dist-info/WHEEL
pyxela-0.0.0.dist-info/licenses/LICENSE
pyxela-0.0.0.dist-info/RECORD
